<Objects>
 <Transfer Name="hari_1" Type="90" cellX="2" cellY="1">
  <Points>
   <Point Pos="2169.9263,1499.1672,551.48218"/>
   <Point Pos="2168.5447,1490.6252,550.95117"/>
   <Point Pos="2167.0769,1485.5535,550.90698"/>
   <Point Pos="2164.1948,1477.0011,550.86176"/>
   <Point Pos="2162.2053,1471.0331,550.9281"/>
   <Point Pos="2158.2004,1465.5647,551.04547"/>
   <Point Pos="2152.9702,1460.4519,551.1012"/>
   <Point Pos="2147.4702,1458.1366,551.17535"/>
   <Point Pos="2140.509,1450.7386,551.28705"/>
   <Point Pos="2132.7886,1441.3341,551.14252"/>
   <Point Pos="2129.3694,1436.1288,550.8418"/>
   <Point Pos="2125.5803,1431.0243,550.4082"/>
   <Point Pos="2119.6558,1426.2655,549.67902"/>
   <Point Pos="2117.0642,1421.9073,549.09644"/>
   <Point Pos="2114.27,1416.9832,548.40375"/>
   <Point Pos="2110.2698,1411.6194,547.45129"/>
   <Point Pos="2105.5488,1407.6866,546.53363"/>
   <Point Pos="2102.5022,1402.9048,545.65332"/>
   <Point Pos="2099.8687,1398.9369,544.89343"/>
   <Point Pos="2094.6965,1394.281,543.76563"/>
   <Point Pos="2092.2092,1391.8541,543.23193"/>
   <Point Pos="2089.1641,1386.9077,542.26508"/>
   <Point Pos="2087.1199,1383.0582,541.5899"/>
   <Point Pos="2084.3206,1375.7015,540.42395"/>
   <Point Pos="2082.0889,1370.1125,539.50519"/>
   <Point Pos="2079.4893,1366.2786,538.86243"/>
   <Point Pos="2074.396,1357.7769,537.7312"/>
   <Point Pos="2069.1597,1352.8657,536.42847"/>
   <Point Pos="2065.4324,1349.1161,534.87958"/>
   <Point Pos="2061.5876,1343.5416,532.6264"/>
   <Point Pos="2059.7671,1338.3187,531.44128"/>
   <Point Pos="2059.9404,1330.45,530.69568"/>
   <Point Pos="2059.7451,1321.8497,530.36481"/>
   <Point Pos="2058.5044,1313.6492,530.43115"/>
   <Point Pos="2057.9724,1306.8499,530.15106"/>
   <Point Pos="2058.0645,1300.9142,529.6568"/>
   <Point Pos="2057.3276,1295.1249,529.56409"/>
   <Point Pos="2056.1948,1289.3163,529.54504"/>
   <Point Pos="2054.6108,1284.3656,529.51025"/>
   <Point Pos="2052.866,1280.3669,529.39441"/>
   <Point Pos="2051.4512,1275.6707,529.17456"/>
   <Point Pos="2051.0845,1270.7507,528.94495"/>
   <Point Pos="2051.4211,1267.7645,528.77545"/>
   <Point Pos="2053.2002,1264.0608,528.65411"/>
   <Point Pos="2055.9475,1260.9336,528.75098"/>
   <Point Pos="2060.4055,1258.3802,529.17743"/>
   <Point Pos="2064.5933,1256.5693,529.81702"/>
   <Point Pos="2068.7021,1255.8525,530.48267"/>
   <Point Pos="2071.9712,1257.062,531.22577"/>
   <Point Pos="2077.2627,1260.1206,532.78046"/>
   <Point Pos="2081.4124,1261.512,534.16406"/>
   <Point Pos="2084.4026,1262.29,535.16541"/>
   <Point Pos="2086.7742,1262.262,535.93787"/>
   <Point Pos="2088.9458,1261.8768,536.638"/>
   <Point Pos="2090.3247,1261.2604,537.01794"/>
   <Point Pos="2094.3845,1260.0546,538.10284"/>
   <Point Pos="2097.3633,1259.2614,538.98053"/>
   <Point Pos="2101.6216,1258.261,540.41846"/>
   <Point Pos="2104.7656,1258.2047,541.71045"/>
   <Point Pos="2108.4792,1258.8983,543.27271"/>
   <Point Pos="2111.2927,1261.109,544.46973"/>
   <Point Pos="2113.3672,1263.4618,545.31079"/>
   <Point Pos="2115.4614,1265.1193,546.13654"/>
   <Point Pos="2117.624,1265.8191,546.85754"/>
   <Point Pos="2120.8801,1265.2771,547.66663"/>
   <Point Pos="2124.1218,1264.2294,548.34155"/>
   <Point Pos="2126.2798,1263.3607,548.74011"/>
   <Point Pos="2128.1304,1263.3462,549.20233"/>
   <Point Pos="2133.7957,1262.7148,550.58899"/>
   <Point Pos="2138.2578,1262.5206,551.89044"/>
   <Point Pos="2148.1282,1261.0302,553.97925"/>
   <Point Pos="2155.8379,1260.9844,555.50378"/>
   <Point Pos="2159.8354,1260.2466,556.10742"/>
   <Point Pos="2165.8835,1257.3962,556.59668"/>
   <Point Pos="2170.7607,1254.1378,556.51556"/>
   <Point Pos="2177.908,1251.9521,556.4082"/>
   <Point Pos="2182.5864,1250.3008,556.21021"/>
   <Point Pos="2189.769,1249.0464,555.89899"/>
   <Point Pos="2195.4204,1248.7139,555.26794"/>
   <Point Pos="2202.5857,1249.826,554.96985"/>
   <Point Pos="2209.6633,1250.7571,554.57642"/>
   <Point Pos="2215.592,1252.4154,554.65338"/>
   <Point Pos="2222.3723,1253.8475,554.46722"/>
   <Point Pos="2229.9314,1254.3844,554.42249"/>
   <Point Pos="2235.3718,1254.6705,554.37543"/>
   <Point Pos="2241.3235,1255.6719,554.31104"/>
   <Point Pos="2245.4026,1256.5867,554.28894"/>
   <Point Pos="2248.6021,1256.2457,554.28894"/>
   <Point Pos="2251.1777,1255.2261,554.28894"/>
   <Point Pos="2253.6675,1253.3317,554.28894"/>
   <Point Pos="2256.3726,1251.7659,554.2749"/>
   <Point Pos="2259.6809,1251.2178,554.21649"/>
   <Point Pos="2262.3394,1250.1139,553.99091"/>
   <Point Pos="2265.3379,1250.5229,554.14307"/>
   <Point Pos="2268.1453,1251.5895,554.48889"/>
   <Point Pos="2269.3357,1253.1196,554.85272"/>
   <Point Pos="2270.3198,1256.099,555.67804"/>
   <Point Pos="2270.6387,1260.0162,556.9762"/>
   <Point Pos="2271.0513,1265.8169,558.81158"/>
   <Point Pos="2271.489,1269.3529,559.79865"/>
   <Point Pos="2273.7136,1273.3082,560.99036"/>
   <Point Pos="2276.5791,1275.8146,561.93585"/>
   <Point Pos="2283.5093,1281.5741,564.88617"/>
   <Point Pos="2287.7732,1286.3719,566.68921"/>
   <Point Pos="2291.0061,1290.2996,567.5741"/>
   <Point Pos="2293.8181,1293.7356,567.95703"/>
   <Point Pos="2297.969,1297.7262,568.74017"/>
   <Point Pos="2301.8999,1300.5653,569.31812"/>
   <Point Pos="2306.2302,1302.0474,569.55377"/>
   <Point Pos="2313.5994,1305.6792,569.78119"/>
   <Point Pos="2320.6392,1309.6564,570.35291"/>
   <Point Pos="2326.9253,1312.5055,571.45618"/>
   <Point Pos="2331.2603,1315.125,572.0318"/>
   <Point Pos="2335.4871,1316.764,572.17773"/>
   <Point Pos="2339.9907,1317.1576,572.23309"/>
   <Point Pos="2347.481,1317.8778,572.40137"/>
   <Point Pos="2354.2014,1318.609,572.80548"/>
   <Point Pos="2362.0679,1320.2725,573.48553"/>
   <Point Pos="2366.3967,1320.9176,573.90417"/>
   <Point Pos="2372.0439,1320.823,574.54218"/>
   <Point Pos="2376.1748,1319.8857,575.00244"/>
   <Point Pos="2380.1821,1318.4076,575.50183"/>
   <Point Pos="2386.0515,1318.3494,576.2276"/>
   <Point Pos="2391.7046,1318.7574,576.93921"/>
   <Point Pos="2395.4565,1319.5032,577.42401"/>
   <Point Pos="2400.5552,1319.8931,578.11243"/>
   <Point Pos="2404.4136,1320.1125,578.60059"/>
   <Point Pos="2407.8582,1319.361,579.1062"/>
   <Point Pos="2411.6064,1317.9711,579.67126"/>
   <Point Pos="2414.7734,1317.1497,580.12561"/>
   <Point Pos="2417.9241,1317.2521,580.55347"/>
   <Point Pos="2420.9287,1317.5439,580.99664"/>
   <Point Pos="2425.6211,1317.2374,581.69434"/>
   <Point Pos="2428.9045,1314.6034,582.24475"/>
   <Point Pos="2440.0908,1310.4314,583.99512"/>
   <Point Pos="2444.1169,1309.0858,584.77869"/>
   <Point Pos="2452.166,1305.4384,586.54449"/>
   <Point Pos="2455.7419,1304.8575,587.24341"/>
   <Point Pos="2459.217,1302.5188,587.98145"/>
   <Point Pos="2463.2451,1299.2186,588.88123"/>
   <Point Pos="2465.9602,1297.2344,589.45154"/>
   <Point Pos="2471.9268,1293.8149,590.72095"/>
   <Point Pos="2478.1631,1290.2196,592.04523"/>
   <Point Pos="2484.7795,1287.6658,593.47229"/>
   <Point Pos="2489.6914,1286.2805,594.63593"/>
   <Point Pos="2494.6943,1283.2198,596.12506"/>
   <Point Pos="2498.6531,1279.9976,597.40863"/>
   <Point Pos="2501.4431,1277.9764,598.17529"/>
   <Point Pos="2504.9307,1276.5802,598.93585"/>
   <Point Pos="2507.7095,1275.1831,599.45813"/>
   <Point Pos="2510.7588,1275.2322,599.84491"/>
   <Point Pos="2514.6318,1274.3716,600.26837"/>
   <Point Pos="2517.5798,1273.4211,600.58875"/>
   <Point Pos="2520.1536,1272.7166,600.86597"/>
   <Point Pos="2524.4678,1270.9862,601.20807"/>
   <Point Pos="2527.8352,1269.3721,601.4093"/>
   <Point Pos="2531.5139,1267.8301,601.50348"/>
   <Point Pos="2535.6589,1265.7201,601.45856"/>
   <Point Pos="2539.4802,1264.4911,601.25696"/>
   <Point Pos="2545.7656,1262.2161,600.62695"/>
   <Point Pos="2550.9612,1259.9404,599.85181"/>
   <Point Pos="2558.9521,1256.4373,598.40259"/>
   <Point Pos="2565.0154,1254.0681,597.23163"/>
   <Point Pos="2576.2007,1250.5917,594.98041"/>
   <Point Pos="2590.1292,1246.9182,592.53821"/>
   <Point Pos="2601.1216,1243.5697,591.38574"/>
   <Point Pos="2609.0984,1240.9456,591.73071"/>
   <Point Pos="2615.0339,1238.6592,592.53802"/>
   <Point Pos="2619.7141,1238.8699,593.18018"/>
   <Point Pos="2625.6497,1239.0126,593.99487"/>
   <Point Pos="2630.3884,1238.0054,594.62622"/>
   <Point Pos="2636.1528,1236.6111,595.29376"/>
   <Point Pos="2645.0691,1236.339,595.95032"/>
   <Point Pos="2654.3867,1236.933,596.91541"/>
   <Point Pos="2663.4102,1235.9702,597.86511"/>
   <Point Pos="2674.4873,1234.7148,599.07983"/>
   <Point Pos="2681.5112,1234.119,599.74445"/>
   <Point Pos="2689.5664,1234.0594,600.44037"/>
   <Point Pos="2700.9243,1232.7889,601.50323"/>
   <Point Pos="2710.6812,1232.469,602.15552"/>
   <Point Pos="2720.8521,1232.7473,602.7832"/>
   <Point Pos="2726.2092,1232.9404,603.14563"/>
   <Point Pos="2732.0649,1233.9344,603.48053"/>
   <Point Pos="2736.3484,1234.8707,603.69458"/>
   <Point Pos="2743.4524,1235.1299,603.86786"/>
   <Point Pos="2747.7744,1234.9259,603.92804"/>
   <Point Pos="2752.8306,1236.3363,604.28796"/>
   <Point Pos="2758.2952,1239.3557,604.5658"/>
   <Point Pos="2765.4434,1243.8048,604.54663"/>
   <Point Pos="2786.5815,1257.2732,603.61237"/>
   <Point Pos="2797.6575,1264.9226,602.89697"/>
   <Point Pos="2806.48,1271.1488,602.22729"/>
   <Point Pos="2813.8833,1275.9731,601.4942"/>
   <Point Pos="2823.3027,1279.6249,600.49512"/>
   <Point Pos="2835.8665,1283.026,599.13904"/>
   <Point Pos="2845.137,1286.4009,598.23169"/>
   <Point Pos="2852.8391,1287.1189,597.69958"/>
   <Point Pos="2864.2349,1283.5282,597.35669"/>
   <Point Pos="2870.4707,1279.0618,597.81775"/>
   <Point Pos="2875.6931,1269.934,597.84235"/>
   <Point Pos="2879.8901,1266.8667,597.69794"/>
   <Point Pos="2886.8206,1263.4327,597.43604"/>
   <Point Pos="2890.0332,1258.7948,597.19739"/>
   <Point Pos="2890.6094,1253.1082,597.18958"/>
   <Point Pos="2890.2214,1249.0482,597.07703"/>
   <Point Pos="2890.3062,1243.3229,596.63501"/>
   <Point Pos="2891.2939,1237.2206,595.63159"/>
   <Point Pos="2890.5867,1230.8969,594.49829"/>
   <Point Pos="2887.625,1222.5635,592.82422"/>
   <Point Pos="2885.5955,1216.6278,591.75427"/>
   <Point Pos="2883.8955,1213.4291,591.1377"/>
   <Point Pos="2879.6226,1208.6238,590.19177"/>
   <Point Pos="2875.6904,1202.2261,589.2655"/>
   <Point Pos="2874.2043,1195.4814,588.72742"/>
   <Point Pos="2873.7053,1188.3438,588.05579"/>
   <Point Pos="2871.9719,1177.7792,586.75696"/>
   <Point Pos="2871.4709,1169.8351,585.25073"/>
   <Point Pos="2870.6721,1162.7369,583.09058"/>
   <Point Pos="2869.4822,1156.3582,580.45935"/>
   <Point Pos="2867.7498,1151.4436,578.13196"/>
   <Point Pos="2864.6709,1145.1995,575.35095"/>
   <Point Pos="2861.4272,1140.5277,573.1485"/>
   <Point Pos="2859.1604,1135.9869,571.19519"/>
   <Point Pos="2859.1235,1130.2318,569.62549"/>
   <Point Pos="2861.2917,1120.9618,568.3667"/>
   <Point Pos="2865.406,1113.3438,567.69086"/>
   <Point Pos="2869.9092,1109.1871,566.39655"/>
   <Point Pos="2874.4858,1104.7013,564.33911"/>
   <Point Pos="2879.1687,1101.0654,562.47791"/>
   <Point Pos="2882.8208,1097.701,561.46021"/>
   <Point Pos="2887.7109,1091.8883,559.92859"/>
  </Points>
 </Transfer>
 <Transfer Name="hari_2" Type="0" cellX="2" cellY="1">
  <Points>
   <Point Pos="2888.1135,1092.2942,559.99066"/>
   <Point Pos="2884.7017,1096.4594,561.15424"/>
   <Point Pos="2878.5491,1102.8984,563.10229"/>
   <Point Pos="2875.718,1104.198,563.91687"/>
   <Point Pos="2874.1248,1105.3158,564.60083"/>
   <Point Pos="2870.668,1108.7145,566.14764"/>
   <Point Pos="2865.9521,1113.0885,567.5741"/>
   <Point Pos="2864.5276,1114.6553,567.89014"/>
   <Point Pos="2862.6072,1117.8716,568.23877"/>
   <Point Pos="2861.2881,1121.2549,568.38806"/>
   <Point Pos="2859.0886,1129.7446,569.53613"/>
   <Point Pos="2859.1814,1135.8634,571.18427"/>
   <Point Pos="2861.4097,1140.2152,573.06671"/>
   <Point Pos="2864.48,1144.6661,575.16241"/>
   <Point Pos="2867.7661,1151.2958,578.12097"/>
   <Point Pos="2869.665,1156.0317,580.40155"/>
   <Point Pos="2870.6355,1162.4142,583.00751"/>
   <Point Pos="2871.6138,1169.8263,585.26599"/>
   <Point Pos="2872.0806,1177.677,586.74951"/>
   <Point Pos="2873.636,1188.2756,588.06036"/>
   <Point Pos="2874.1768,1195.3073,588.71643"/>
   <Point Pos="2875.7749,1201.3983,589.18762"/>
   <Point Pos="2877.0654,1204.2166,589.51477"/>
   <Point Pos="2879.6909,1208.4675,590.18195"/>
   <Point Pos="2883.4089,1212.7371,591.02515"/>
   <Point Pos="2885.0056,1215.3864,591.5658"/>
   <Point Pos="2886.229,1218.5337,592.11292"/>
   <Point Pos="2887.8076,1223.1992,592.96582"/>
   <Point Pos="2890.4939,1230.1414,594.36792"/>
   <Point Pos="2890.9951,1233.9862,595.08563"/>
   <Point Pos="2890.936,1237.8348,595.74817"/>
   <Point Pos="2890.2493,1243.2416,596.63391"/>
   <Point Pos="2890.21,1248.0424,597.04462"/>
   <Point Pos="2890.1946,1250.1785,597.11926"/>
   <Point Pos="2890.6633,1253.0665,597.18854"/>
   <Point Pos="2890.4414,1257.098,597.19495"/>
   <Point Pos="2889.9885,1258.9161,597.19971"/>
   <Point Pos="2888.8044,1261.3694,597.29974"/>
   <Point Pos="2886.9231,1263.3849,597.42969"/>
   <Point Pos="2884.2695,1264.8447,597.55957"/>
   <Point Pos="2879.6143,1266.9902,597.70917"/>
   <Point Pos="2876.4207,1268.5962,597.78387"/>
   <Point Pos="2874.9241,1270.365,597.83459"/>
   <Point Pos="2872.9766,1274.1365,597.88898"/>
   <Point Pos="2870.49,1278.9081,597.81836"/>
   <Point Pos="2868.8926,1280.6565,597.56555"/>
   <Point Pos="2864.0725,1283.6998,597.35303"/>
   <Point Pos="2860.5789,1285.1382,597.44397"/>
   <Point Pos="2853.0142,1287.1798,597.68652"/>
   <Point Pos="2841.9155,1285.295,598.5011"/>
   <Point Pos="2831.2864,1281.8405,599.5943"/>
   <Point Pos="2822.5889,1279.2618,600.56342"/>
   <Point Pos="2814.2312,1275.9276,601.45258"/>
   <Point Pos="2806.1211,1270.8307,602.2514"/>
   <Point Pos="2797.6655,1265.2577,602.87976"/>
   <Point Pos="2786.3298,1257.26,603.61273"/>
   <Point Pos="2778.6382,1251.2349,604.17859"/>
   <Point Pos="2769.8083,1246.0449,604.40948"/>
   <Point Pos="2763.4402,1242.1561,604.58618"/>
   <Point Pos="2756.7312,1238.1166,604.52203"/>
   <Point Pos="2753.6182,1236.4155,604.33783"/>
   <Point Pos="2747.6548,1234.8596,603.92413"/>
   <Point Pos="2742.1709,1235.1873,603.88232"/>
   <Point Pos="2736.457,1234.9468,603.6969"/>
   <Point Pos="2725.812,1233.0039,603.12341"/>
   <Point Pos="2710.53,1232.5116,602.13989"/>
   <Point Pos="2700.8452,1232.8998,601.47058"/>
   <Point Pos="2689.1072,1233.8416,600.42865"/>
   <Point Pos="2680.5107,1234.4164,599.6452"/>
   <Point Pos="2673.5054,1234.9532,598.95367"/>
   <Point Pos="2663.1741,1235.8975,597.83984"/>
   <Point Pos="2654.6465,1236.8503,596.93781"/>
   <Point Pos="2644.1475,1236.0688,595.85516"/>
   <Point Pos="2640.0466,1235.6852,595.61041"/>
   <Point Pos="2634.2078,1236.8591,595.08765"/>
   <Point Pos="2626.1394,1239.0604,594.04663"/>
   <Point Pos="2621.7371,1239.0134,593.48541"/>
   <Point Pos="2615.4126,1238.4885,592.59027"/>
   <Point Pos="2609.5955,1240.752,591.79492"/>
   <Point Pos="2598.1367,1244.4548,591.56995"/>
   <Point Pos="2576.6304,1250.2451,594.87592"/>
   <Point Pos="2565.2605,1253.9153,597.17303"/>
   <Point Pos="2551.2666,1259.6974,599.79755"/>
   <Point Pos="2543.5325,1262.8058,600.86975"/>
   <Point Pos="2536.0183,1265.4342,601.43701"/>
   <Point Pos="2527.9114,1269.2323,601.41028"/>
   <Point Pos="2519.7214,1272.6846,600.82593"/>
   <Point Pos="2515.7339,1274.2096,600.3717"/>
   <Point Pos="2512.137,1274.9066,599.98596"/>
   <Point Pos="2508.5664,1275.1906,599.55457"/>
   <Point Pos="2504.3252,1276.6697,598.81732"/>
   <Point Pos="2501.1804,1278.3879,598.06598"/>
   <Point Pos="2494.5715,1283.2721,596.07825"/>
   <Point Pos="2489.4783,1286.2955,594.58142"/>
   <Point Pos="2477.6797,1290.2295,591.95776"/>
   <Point Pos="2466.1006,1297.1743,589.47559"/>
   <Point Pos="2459.5354,1302.7128,588.02295"/>
   <Point Pos="2455.583,1304.7153,587.21741"/>
   <Point Pos="2445.1326,1308.7908,585.0155"/>
   <Point Pos="2440.0645,1310.63,583.99219"/>
   <Point Pos="2436.5603,1311.2849,583.43909"/>
   <Point Pos="2429.0071,1314.5326,582.26172"/>
   <Point Pos="2423.8542,1317.647,581.40643"/>
   <Point Pos="2413.8975,1317.74,579.9704"/>
   <Point Pos="2403.6523,1320.2429,578.48376"/>
   <Point Pos="2395.0776,1319.5621,577.3728"/>
   <Point Pos="2381.741,1318.6891,575.69189"/>
   <Point Pos="2373.0725,1320.3324,574.63824"/>
   <Point Pos="2356.7859,1318.74,573.0177"/>
   <Point Pos="2335.7249,1316.3964,572.17395"/>
   <Point Pos="2325.303,1311.912,571.18677"/>
   <Point Pos="2316.144,1307.0342,569.89996"/>
   <Point Pos="2305.3491,1301.4358,569.50757"/>
   <Point Pos="2293.5425,1293.0203,567.91211"/>
   <Point Pos="2287.7776,1286.2424,566.68469"/>
   <Point Pos="2282.4675,1280.8888,564.51501"/>
   <Point Pos="2273.8496,1273.1174,560.99536"/>
   <Point Pos="2271.7202,1269.1688,559.81415"/>
   <Point Pos="2270.5713,1261.8363,557.56787"/>
   <Point Pos="2270.6487,1257.7943,556.29413"/>
   <Point Pos="2269.2959,1253.407,554.93164"/>
   <Point Pos="2265.4314,1250.005,554.08075"/>
   <Point Pos="2260.4246,1250.7819,554.15155"/>
   <Point Pos="2253.6475,1253.514,554.28528"/>
   <Point Pos="2249.8088,1256.0668,554.28528"/>
   <Point Pos="2244.1191,1256.6329,554.28528"/>
   <Point Pos="2233.3364,1254.2417,554.41681"/>
   <Point Pos="2216.542,1251.7,554.62115"/>
   <Point Pos="2202.6963,1249.7169,554.94824"/>
   <Point Pos="2196.3445,1248.0913,555.12732"/>
   <Point Pos="2189.3462,1248.8533,555.86768"/>
   <Point Pos="2181.9673,1250.2625,556.24646"/>
   <Point Pos="2170.4917,1253.9231,556.51447"/>
   <Point Pos="2165.5271,1257.3708,556.57202"/>
   <Point Pos="2160.2561,1260.0907,556.15613"/>
   <Point Pos="2152.4297,1260.6267,554.77197"/>
   <Point Pos="2138.2693,1262.4146,551.89783"/>
   <Point Pos="2126.6426,1263.4041,548.84814"/>
   <Point Pos="2123.5027,1264.4945,548.24023"/>
   <Point Pos="2120.2263,1265.359,547.53149"/>
   <Point Pos="2116.7563,1265.5405,546.60266"/>
   <Point Pos="2113.1318,1262.8925,545.21191"/>
   <Point Pos="2110.2852,1260.5159,544.06592"/>
   <Point Pos="2106.0203,1258.6167,542.29315"/>
   <Point Pos="2100.0376,1258.2385,539.78955"/>
   <Point Pos="2095.1555,1259.6337,538.31158"/>
   <Point Pos="2089.9707,1261.3101,536.93237"/>
   <Point Pos="2086.0581,1262.2456,535.70032"/>
   <Point Pos="2082.1521,1261.8401,534.40942"/>
   <Point Pos="2076.0996,1259.6143,532.39935"/>
   <Point Pos="2071.7734,1256.6505,531.18555"/>
   <Point Pos="2067.355,1255.7419,530.255"/>
   <Point Pos="2064.3474,1256.2639,529.77985"/>
   <Point Pos="2059.5525,1258.5562,529.06824"/>
   <Point Pos="2055.8044,1261.0668,528.7442"/>
   <Point Pos="2052.9868,1264.1638,528.64618"/>
   <Point Pos="2051.4912,1266.7571,528.69714"/>
   <Point Pos="2050.8936,1270.8728,528.93866"/>
   <Point Pos="2051.4609,1275.9739,529.19867"/>
   <Point Pos="2052.5459,1280.7081,529.39575"/>
   <Point Pos="2054.5332,1285.4424,529.54138"/>
   <Point Pos="2056.4028,1289.4587,529.54138"/>
   <Point Pos="2057.613,1293.6018,529.55603"/>
   <Point Pos="2058.4438,1299.8507,529.58459"/>
   <Point Pos="2057.9231,1306.3745,530.12256"/>
   <Point Pos="2058.3035,1313.5999,530.42267"/>
   <Point Pos="2059.0078,1319.5533,530.38983"/>
   <Point Pos="2059.7952,1323.5806,530.36206"/>
   <Point Pos="2059.6938,1328.6049,530.59851"/>
   <Point Pos="2059.543,1338.069,531.4035"/>
   <Point Pos="2060.2986,1341.3918,532.0343"/>
   <Point Pos="2061.3674,1343.5892,532.63562"/>
   <Point Pos="2065.7454,1349.1356,534.95642"/>
   <Point Pos="2069.8882,1353.8392,536.76465"/>
   <Point Pos="2074.4724,1358.1581,537.78632"/>
   <Point Pos="2078.2639,1364.3186,538.62439"/>
   <Point Pos="2082.4917,1371.204,539.72113"/>
   <Point Pos="2087.0679,1382.5861,541.53595"/>
   <Point Pos="2089.5393,1387.7618,542.41394"/>
   <Point Pos="2093.3389,1393.424,543.54303"/>
   <Point Pos="2097.4116,1396.6304,544.3728"/>
   <Point Pos="2100.4526,1399.3969,545.02875"/>
   <Point Pos="2105.8396,1407.6345,546.56451"/>
   <Point Pos="2109.9502,1410.8025,547.33142"/>
   <Point Pos="2113.5559,1414.5438,548.07715"/>
   <Point Pos="2116.0679,1419.1086,548.78168"/>
   <Point Pos="2119.5647,1425.3083,549.57617"/>
   <Point Pos="2123.0181,1429.3794,550.12988"/>
   <Point Pos="2126.7075,1431.4863,550.47498"/>
   <Point Pos="2129.8079,1435.8783,550.84308"/>
   <Point Pos="2135.3,1444.8912,551.24677"/>
   <Point Pos="2140.397,1450.6079,551.28705"/>
   <Point Pos="2146.8474,1457.5281,551.20587"/>
   <Point Pos="2153.762,1461.6099,551.09753"/>
   <Point Pos="2158.3625,1465.9781,551.03333"/>
   <Point Pos="2162.0837,1471.0687,550.91876"/>
   <Point Pos="2163.1721,1474.5243,550.85638"/>
   <Point Pos="2166.5593,1484.4016,550.90686"/>
   <Point Pos="2168.0813,1489.1674,550.94104"/>
   <Point Pos="2169.8733,1499.4915,551.50488"/>
  </Points>
 </Transfer>
</Objects>
